kerblwelt_api/__init__.py
kerblwelt_api/auth.py
kerblwelt_api/client.py
kerblwelt_api/const.py
kerblwelt_api/exceptions.py
kerblwelt_api/models.py
kerblwelt_api-0.1.0.dist-info/licenses/LICENSE
kerblwelt_api-0.1.0.dist-info/METADATA
kerblwelt_api-0.1.0.dist-info/WHEEL
kerblwelt_api-0.1.0.dist-info/top_level.txt
kerblwelt_api-0.1.0.dist-info/RECORD
