Metadata-Version: 2.4
Name: kerblwelt-api
Version: 0.1.0
Summary: Python API client for Kerbl Welt IoT platform (AKO Smart Satellite electric fence monitors)
Author-email: Steve Garrity <sgarrity@gmail.com>
License: MIT
Project-URL: Homepage, https://github.com/stgarrity/kerblwelt-api
Project-URL: Repository, https://github.com/stgarrity/kerblwelt-api
Project-URL: Issues, https://github.com/stgarrity/kerblwelt-api/issues
Keywords: kerbl,ako,smart-satellite,electric-fence,iot,api-client
Classifier: Development Status :: 3 - Alpha
Classifier: Intended Audience :: Developers
Classifier: License :: OSI Approved :: MIT License
Classifier: Programming Language :: Python :: 3
Classifier: Programming Language :: Python :: 3.11
Classifier: Programming Language :: Python :: 3.12
Classifier: Programming Language :: Python :: 3.13
Classifier: Topic :: Home Automation
Classifier: Topic :: Software Development :: Libraries :: Python Modules
Requires-Python: >=3.11
License-File: LICENSE
Requires-Dist: aiohttp>=3.9.0
Provides-Extra: dev
Requires-Dist: pytest>=7.0; extra == "dev"
Requires-Dist: pytest-aiohttp>=1.0.0; extra == "dev"
Requires-Dist: pytest-asyncio>=0.21.0; extra == "dev"
Requires-Dist: pytest-cov>=4.0.0; extra == "dev"
Requires-Dist: black>=23.0.0; extra == "dev"
Requires-Dist: ruff>=0.1.0; extra == "dev"
Requires-Dist: mypy>=1.0.0; extra == "dev"
Dynamic: license-file
